mcp_star_demo/__init__.py
mcp_star_demo/py.typed
mcp_star_demo/server.py
mcp_star_demo-0.1.1.dist-info/METADATA
mcp_star_demo-0.1.1.dist-info/WHEEL
mcp_star_demo-0.1.1.dist-info/entry_points.txt
mcp_star_demo-0.1.1.dist-info/RECORD
