Metadata-Version: 2.4
Name: mcp-star-demo
Version: 0.1.1
Summary: Add your description here
Author-email: "kaiming.zhang" <kaiming.zhang@transwarp.io>
Requires-Python: >=3.10
Requires-Dist: mcp[cli]>=1.11.0
